{
  "$schema": "https://developer.microsoft.com/json-schemas/fabric/item/report/definition/visualContainer/2.7.0/schema.json",
  "name": "aa10f66bae505d954987",
  "position": {
    "x": 0,
    "y": 0,
    "z": 2000,
    "height": 28.550185873605948,
    "width": 220,
    "tabOrder": 0
  },
  "visual": {
    "visualType": "actionButton",
    "objects": {
      "icon": [
        {
          "properties": {
            "shapeType": {
              "expr": {
                "Literal": {
                  "Value": "'custom'"
                }
              }
            },
            "image": {
              "image": {
                "name": {
                  "expr": {
                    "Literal": {
                      "Value": "'icon_visswitch_tableheader_selected.svg'"
                    }
                  }
                },
                "url": {
                  "expr": {
                    "ResourcePackageItem": {
                      "PackageName": "RegisteredResources",
                      "PackageType": 1,
                      "ItemName": "icon_visswitch_tableheader_sel8196834901575957.svg"
                    }
                  }
                },
                "scaling": {
                  "expr": {
                    "Literal": {
                      "Value": "'Normal'"
                    }
                  }
                }
              }
            }
          },
          "selector": {
            "id": "default"
          }
        },
        {
          "properties": {
            "show": {
              "expr": {
                "Literal": {
                  "Value": "true"
                }
              }
            }
          }
        },
        {
          "properties": {
            "image": {
              "image": {
                "name": {
                  "expr": {
                    "Literal": {
                      "Value": "'icon_visswitch_tableheader_selected.svg'"
                    }
                  }
                },
                "url": {
                  "expr": {
                    "ResourcePackageItem": {
                      "PackageName": "RegisteredResources",
                      "PackageType": 1,
                      "ItemName": "icon_visswitch_tableheader_sel1441715721518.svg"
                    }
                  }
                },
                "scaling": {
                  "expr": {
                    "Literal": {
                      "Value": "'Normal'"
                    }
                  }
                }
              }
            }
          },
          "selector": {
            "id": "hover"
          }
        }
      ],
      "outline": [
        {
          "properties": {
            "show": {
              "expr": {
                "Literal": {
                  "Value": "false"
                }
              }
            }
          }
        }
      ],
      "text": [
        {
          "properties": {
            "show": {
              "expr": {
                "Literal": {
                  "Value": "true"
                }
              }
            }
          }
        },
        {
          "properties": {
            "text": {
              "expr": {
                "Literal": {
                  "Value": "'Sustainability Scorecard'"
                }
              }
            },
            "horizontalAlignment": {
              "expr": {
                "Literal": {
                  "Value": "'center'"
                }
              }
            },
            "fontColor": {
              "solid": {
                "color": {
                  "expr": {
                    "Literal": {
                      "Value": "'#333333'"
                    }
                  }
                }
              }
            },
            "topMargin": {
              "expr": {
                "Literal": {
                  "Value": "7L"
                }
              }
            },
            "leftMargin": {
              "expr": {
                "Literal": {
                  "Value": "31L"
                }
              }
            },
            "bold": {
              "expr": {
                "Literal": {
                  "Value": "true"
                }
              }
            }
          },
          "selector": {
            "id": "default"
          }
        },
        {
          "properties": {
            "bold": {
              "expr": {
                "Literal": {
                  "Value": "true"
                }
              }
            },
            "fontColor": {
              "solid": {
                "color": {
                  "expr": {
                    "Literal": {
                      "Value": "'#333333'"
                    }
                  }
                }
              }
            }
          },
          "selector": {
            "id": "hover"
          }
        }
      ]
    },
    "visualContainerObjects": {
      "padding": [
        {
          "properties": {
            "top": {
              "expr": {
                "Literal": {
                  "Value": "0D"
                }
              }
            },
            "bottom": {
              "expr": {
                "Literal": {
                  "Value": "0D"
                }
              }
            },
            "right": {
              "expr": {
                "Literal": {
                  "Value": "0D"
                }
              }
            },
            "left": {
              "expr": {
                "Literal": {
                  "Value": "0D"
                }
              }
            }
          }
        }
      ],
      "border": [
        {
          "properties": {
            "radius": {
              "expr": {
                "Literal": {
                  "Value": "0D"
                }
              }
            },
            "show": {
              "expr": {
                "Literal": {
                  "Value": "false"
                }
              }
            }
          }
        }
      ],
      "background": [
        {
          "properties": {
            "show": {
              "expr": {
                "Literal": {
                  "Value": "false"
                }
              }
            }
          }
        }
      ],
      "title": [
        {
          "properties": {
            "text": {
              "expr": {
                "Literal": {
                  "Value": "'Visual Selected'"
                }
              }
            }
          }
        }
      ],
      "visualHeader": [
        {
          "properties": {
            "show": {
              "expr": {
                "Literal": {
                  "Value": "false"
                }
              }
            }
          }
        }
      ],
      "visualLink": [
        {
          "properties": {
            "show": {
              "expr": {
                "Literal": {
                  "Value": "false"
                }
              }
            },
            "type": {
              "expr": {
                "Literal": {
                  "Value": "'PageNavigation'"
                }
              }
            },
            "navigationSection": {
              "expr": {
                "Literal": {
                  "Value": "'6a6a695ba29172a96cec'"
                }
              }
            },
            "tooltip": {
              "expr": {
                "Literal": {
                  "Value": "'Switch to Visual Mode'"
                }
              }
            }
          }
        }
      ]
    },
    "drillFilterOtherVisuals": true
  },
  "parentGroupName": "80de01b046edecbe0ab0",
  "howCreated": "InsertVisualButton"
}